nonebot_plugin_mockingbird/__init__.py
nonebot_plugin_mockingbird/config.py
nonebot_plugin_mockingbird/data_source.py
nonebot_plugin_mockingbird/download.py
nonebot_plugin_mockingbird/resource/config.json
nonebot_plugin_mockingbird/resource/model_list.json
nonebot_plugin_mockingbird-0.2.1.dist-info/LICENSE
nonebot_plugin_mockingbird-0.2.1.dist-info/WHEEL
nonebot_plugin_mockingbird-0.2.1.dist-info/METADATA
nonebot_plugin_mockingbird-0.2.1.dist-info/RECORD
