Metadata-Version: 2.1
Name: nonebot-plugin-mockingbird
Version: 0.2.1
Summary: 利用MockingBird生成语音并发送
Home-page: https://github.com/AkashiCoin/nonebot_plugin_mockingbird
License: MIT
Keywords: MockingBird,nonebot
Author: AkashiCoin
Author-email: l1040186796@gmail.com
Requires-Python: >=3.8,<3.10
Classifier: License :: OSI Approved :: MIT License
Classifier: Programming Language :: Python :: 3
Classifier: Programming Language :: Python :: 3.8
Classifier: Programming Language :: Python :: 3.9
Requires-Dist: aiofile (>=3.7.4,<4.0.0)
Requires-Dist: httpx (>=0.22.0,<0.23.0)
Requires-Dist: langid (>=1.1.0,<2.0.0)
Requires-Dist: mockingbirdforuse (>=0.2.3,<0.3.0)
Requires-Dist: nonebot-adapter-onebot (>=2.0.0-beta.1,<3.0.0)
Requires-Dist: nonebot2 (>=2.0.0b1,<3.0.0)
Requires-Dist: pydub (>=0.25.0,<0.26.0)
Project-URL: Repository, https://github.com/AkashiCoin/nonebot_plugin_mockingbird
